{"pattern": [{"iteration": [{"coord": [3, 5], "amplitude": 150, "frequency": 300}], "time": 10}, {"iteration": [{"coord": [3, 5], "amplitude": 195, "frequency": 300}, {"coord": [4, 2], "amplitude": 150, "frequency": 300}, {"coord": [4, 2], "amplitude": 150, "frequency": 300}, {"coord": [3, 5], "amplitude": 150, "frequency": 300}], "time": 10}, {"iteration": [{"coord": [3, 5], "amplitude": 210, "frequency": 300}, {"coord": [4, 2], "amplitude": 195, "frequency": 300}, {"coord": [4, 2], "amplitude": 210, "frequency": 300}, {"coord": [4, 2], "amplitude": 195, "frequency": 300}, {"coord": [4, 2], "amplitude": 195, "frequency": 300}], "time": 10}, {"iteration": [{"coord": [4, 2], "amplitude": 150, "frequency": 300}, {"coord": [3, 5], "amplitude": 139, "frequency": 300}, {"coord": [4, 2], "amplitude": 139, "frequency": 300}, {"coord": [4, 2], "amplitude": 139, "frequency": 300}, {"coord": [3, 5], "amplitude": 139, "frequency": 300}, {"coord": [3, 5], "amplitude": 210, "frequency": 300}], "time": 10}, {"iteration": [{"coord": [4, 2], "amplitude": 248, "frequency": 300}, {"coord": [4, 2], "amplitude": 210, "frequency": 300}], "time": 10}, {"iteration": [{"coord": [4, 2], "amplitude": 150, "frequency": 300}, {"coord": [3, 5], "amplitude": 210, "frequency": 300}, {"coord": [4, 2], "amplitude": 139, "frequency": 300}, {"coord": [4, 2], "amplitude": 210, "frequency": 300}, {"coord": [3, 5], "amplitude": 150, "frequency": 300}, {"coord": [4, 2], "amplitude": 128, "frequency": 300}, {"coord": [4, 2], "amplitude": 248, "frequency": 300}, {"coord": [4, 2], "amplitude": 150, "frequency": 300}, {"coord": [4, 2], "amplitude": 139, "frequency": 300}, {"coord": [4, 2], "amplitude": 128, "frequency": 300}, {"coord": [4, 2], "amplitude": 210, "frequency": 300}], "time": 10}, {"iteration": [{"coord": [4, 2], "amplitude": 230, "frequency": 300}, {"coord": [4, 2], "amplitude": 248, "frequency": 300}], "time": 10}, {"iteration": [{"coord": [3, 5], "amplitude": 128, "frequency": 300}, {"coord": [4, 2], "amplitude": 150, "frequency": 300}, {"coord": [4, 2], "amplitude": 230, "frequency": 300}, {"coord": [3, 5], "amplitude": 171, "frequency": 300}, {"coord": [4, 2], "amplitude": 128, "frequency": 300}, {"coord": [4, 2], "amplitude": 195, "frequency": 300}, {"coord": [4, 2], "amplitude": 128, "frequency": 300}, {"coord": [4, 2], "amplitude": 150, "frequency": 300}, {"coord": [4, 2], "amplitude": 171, "frequency": 300}, {"coord": [4, 2], "amplitude": 128, "frequency": 300}, {"coord": [4, 2], "amplitude": 128, "frequency": 300}, {"coord": [3, 5], "amplitude": 210, "frequency": 300}, {"coord": [4, 2], "amplitude": 128, "frequency": 300}, {"coord": [3, 5], "amplitude": 210, "frequency": 300}, {"coord": [3, 5], "amplitude": 150, "frequency": 300}], "time": 10}, {"iteration": [{"coord": [4, 2], "amplitude": 230, "frequency": 300}, {"coord": [4, 2], "amplitude": 171, "frequency": 300}], "time": 10}, {"iteration": [{"coord": [4, 2], "amplitude": 248, "frequency": 300}, {"coord": [4, 2], "amplitude": 248, "frequency": 300}, {"coord": [4, 2], "amplitude": 230, "frequency": 300}, {"coord": [3, 5], "amplitude": 128, "frequency": 300}, {"coord": [4, 2], "amplitude": 210, "frequency": 300}, {"coord": [3, 5], "amplitude": 195, "frequency": 300}, {"coord": [4, 2], "amplitude": 128, "frequency": 300}, {"coord": [3, 5], "amplitude": 210, "frequency": 300}, {"coord": [3, 5], "amplitude": 150, "frequency": 300}, {"coord": [4, 2], "amplitude": 150, "frequency": 300}], "time": 10}, {"iteration": [{"coord": [4, 2], "amplitude": 150, "frequency": 300}, {"coord": [3, 5], "amplitude": 171, "frequency": 300}, {"coord": [3, 5], "amplitude": 139, "frequency": 300}, {"coord": [4, 2], "amplitude": 150, "frequency": 300}, {"coord": [4, 2], "amplitude": 248, "frequency": 300}, {"coord": [3, 5], "amplitude": 150, "frequency": 300}], "time": 10}]}